agcoinstall/__init__.py
agcoinstall/__main__.py
agcoinstall/agcoinstall.log
agcoinstall/data/images/auc_install_finish.png
agcoinstall/data/images/yes.png
agcoinstall/data/SontheimCertificate1.cer
agcoinstall/data/SontheimCertificate2.cer
agcoinstall/py.typed
agcoinstall/request_test.py
agcoinstall/test.py
agcoinstall-0.1.21.dist-info/entry_points.txt
agcoinstall-0.1.21.dist-info/LICENSE.rst
agcoinstall-0.1.21.dist-info/WHEEL
agcoinstall-0.1.21.dist-info/METADATA
agcoinstall-0.1.21.dist-info/RECORD
