Metadata-Version: 2.1
Name: agcoinstall
Version: 0.1.21
Summary: Agcoinstall
Home-page: https://github.com/MrSuperbear/agcoinstall
License: MIT
Author: Darrin Fraser
Author-email: darrin.fraser@agcocorp.com
Requires-Python: >=3.6.1,<4.0.0
Classifier: License :: OSI Approved :: MIT License
Classifier: Programming Language :: Python :: 3
Classifier: Programming Language :: Python :: 3.10
Classifier: Programming Language :: Python :: 3.6
Classifier: Programming Language :: Python :: 3.7
Classifier: Programming Language :: Python :: 3.8
Classifier: Programming Language :: Python :: 3.9
Requires-Dist: arrow (>=1.2.2,<2.0.0)
Requires-Dist: click (>=7.0,<8.0)
Requires-Dist: clumper (>=0.2.15,<0.3.0)
Requires-Dist: lxml (>=4.6.2,<5.0.0)
Requires-Dist: psutil (>=5.7.3,<6.0.0)
Requires-Dist: pyautogui (>=0.9.52,<0.10.0)
Requires-Dist: regobj (>=0.2.2,<0.3.0)
Requires-Dist: requests (>=2.24.0,<3.0.0)
Requires-Dist: winapps (>=0.1.6,<0.2.0)
Project-URL: Changelog, https://github.com/MrSuperbear/agcoinstall/releases
Project-URL: Documentation, https://agcoinstall.readthedocs.io
Project-URL: Repository, https://github.com/MrSuperbear/agcoinstall
